smartshare/__init__.py
smartshare/admin.py
smartshare/apps.py
smartshare/forms.py
smartshare/models.py
smartshare/tests.py
smartshare/urls.py
smartshare/utils.py
smartshare/views.py
smartshare/migrations/0001_initial.py
smartshare/migrations/__init__.py
smartshare/static/smartshare/css/base.css
smartshare/static/smartshare/css/bootstrap-grid.css
smartshare/static/smartshare/css/bootstrap-grid.css.map
smartshare/static/smartshare/css/bootstrap-grid.min.css
smartshare/static/smartshare/css/bootstrap-grid.min.css.map
smartshare/static/smartshare/css/bootstrap-reboot.css
smartshare/static/smartshare/css/bootstrap-reboot.css.map
smartshare/static/smartshare/css/bootstrap-reboot.min.css
smartshare/static/smartshare/css/bootstrap-reboot.min.css.map
smartshare/static/smartshare/css/bootstrap.css
smartshare/static/smartshare/css/bootstrap.css.map
smartshare/static/smartshare/css/bootstrap.min.css
smartshare/static/smartshare/css/bootstrap.min.css.map
smartshare/static/smartshare/js/bootstrap.bundle.js
smartshare/static/smartshare/js/bootstrap.bundle.js.map
smartshare/static/smartshare/js/bootstrap.bundle.min.js
smartshare/static/smartshare/js/bootstrap.bundle.min.js.map
smartshare/static/smartshare/js/bootstrap.js
smartshare/static/smartshare/js/bootstrap.js.map
smartshare/static/smartshare/js/bootstrap.min.js
smartshare/static/smartshare/js/bootstrap.min.js.map
smartshare/static/smartshare/js/jquery-3.2.1.slim.min.js
smartshare/static/smartshare/js/popper.min.js
smartshare/templates/smartshare/404.html
smartshare/templates/smartshare/base.html
smartshare/templates/smartshare/delete.html
smartshare/templates/smartshare/location_detail.html
smartshare/templates/smartshare/make_dir.html
smartshare/templates/smartshare/make_file.html
smartshare/templates/smartshare/shared_locations.html
smartshare/templates/smartshare/upload.html
djangosmartshare-0.8.8.dist-info/LICENSE
djangosmartshare-0.8.8.dist-info/METADATA
djangosmartshare-0.8.8.dist-info/WHEEL
djangosmartshare-0.8.8.dist-info/top_level.txt
djangosmartshare-0.8.8.dist-info/RECORD
